torchfunction/__init__.py
torchfunction/createtensor.py
torchfunction/data.py
torchfunction/device.py
torchfunction/functional.py
torchfunction/inspect.py
torchfunction/lossfunc.py
torchfunction/mimc.py
torchfunction/model.py
torchfunction/random.py
torchfunction/running_average.py
torchfunction/select.py
torchfunction/stats.py
torchfunction/utils.py
torchfunction/wrapper.py
torchfunction/nn/__init__.py
torchfunction/nn/linear.py
torchfunction/optim/__init__.py
torchfunction/optim/lr_scheduler.py
torchfunction-0.0.79.dist-info/METADATA
torchfunction-0.0.79.dist-info/WHEEL
torchfunction-0.0.79.dist-info/top_level.txt
torchfunction-0.0.79.dist-info/RECORD
